error_align_fix-0.1.4.dist-info/RECORD
error_align_fix-0.1.4.dist-info/WHEEL
error_align_fix-0.1.4.dist-info/METADATA
error_align/_cpp_beam_search.cpython-314-darwin.so
error_align/__init__.py
error_align/core.py
error_align/beam_search.py
error_align/error_align.py
error_align/utils.py
error_align/graph_metadata.py
error_align/path_to_alignment.py
error_align/_cpp_edit_distance.cpython-314-darwin.so
error_align/edit_distance.py
error_align/backtrace_graph.py
error_align/baselines/optimal_word_alignment.py
error_align/baselines/rapidfuzz_word_alignment.py
error_align/baselines/__init__.py
error_align/baselines/utils.py
error_align/baselines/power_alignment.py
error_align/baselines/power/cmudict.rep.json
error_align/baselines/power/__init__.py
error_align/baselines/power/power/aligner.py
error_align/baselines/power/power/readers.py
error_align/baselines/power/power/punct.py
error_align/baselines/power/power/__init__.py
error_align/baselines/power/power/writers.py
error_align/baselines/power/power/phonemes.py
error_align/baselines/power/power/levenshtein.py
error_align/baselines/power/power/pronounce.py
error_align/baselines/power/normalize/normalize.py
error_align/baselines/power/normalize/__init__.py
error_align/baselines/power/normalize/numbers.py
error_align/baselines/power/normalize/contractions.py
