Metadata-Version: 2.2
Name: error-align-fix
Version: 0.1.4
Summary: Text-to-text alignment algorithm for speech recognition error analysis.
Keywords: speech-recognition,text-alignment,NLP,evaluation
Author-Email: Lasse Borgholt <lb@corti.ai>
License: MIT
Classifier: Programming Language :: Python :: 3
Classifier: Programming Language :: Python :: 3.10
Classifier: Programming Language :: Python :: 3.11
Classifier: Programming Language :: Python :: 3.12
Classifier: Programming Language :: Python :: 3.13
Classifier: Programming Language :: Python :: 3.14
Classifier: License :: OSI Approved :: MIT License
Classifier: Operating System :: OS Independent
Classifier: Topic :: Software Development :: Libraries
Classifier: Topic :: Scientific/Engineering :: Artificial Intelligence
Classifier: Topic :: Text Processing :: Linguistic
Classifier: Intended Audience :: Developers
Classifier: Intended Audience :: Science/Research
Project-URL: Homepage, https://github.com/corticph/error-align
Requires-Python: <3.15,>=3.10
Requires-Dist: tqdm>=4.67.1
Requires-Dist: unidecode>=1.4.0
Requires-Dist: regex>=2025.9.18
Provides-Extra: evaluation
Requires-Dist: rapidfuzz>=3.13.0; python_version == "3.12" and extra == "evaluation"
Requires-Dist: num2words>=0.5.14; python_version == "3.12" and extra == "evaluation"
Requires-Dist: datasets>=3.3.2; python_version == "3.12" and extra == "evaluation"
Requires-Dist: soundfile>=0.13.1; python_version == "3.12" and extra == "evaluation"
Requires-Dist: librosa>=0.11.0; python_version == "3.12" and extra == "evaluation"
Requires-Dist: click>=8.2.1; python_version == "3.12" and extra == "evaluation"
Requires-Dist: pandas>=2.3.1; python_version == "3.12" and extra == "evaluation"
Requires-Dist: scipy>=1.16.1; python_version == "3.12" and extra == "evaluation"
Requires-Dist: textgrid>=1.6.1; python_version == "3.12" and extra == "evaluation"
Requires-Dist: nemo-toolkit[all]>=2.4.0; python_version == "3.12" and extra == "evaluation"
Requires-Dist: transformers>=4.51.3; python_version == "3.12" and extra == "evaluation"
Requires-Dist: backoff>=2.2.1; python_version == "3.12" and extra == "evaluation"
Requires-Dist: gitpython>=3.1.45; python_version == "3.12" and extra == "evaluation"
Requires-Dist: pyphen>=0.17.2; python_version == "3.12" and extra == "evaluation"
Requires-Dist: matplotlib>=3.10.6; python_version == "3.12" and extra == "evaluation"
Requires-Dist: numpy<2.0,>=1.22; python_version == "3.12" and extra == "evaluation"
